{"cn_src_article_sort_shell_index.md":"kvxhPFvC","cn_src_article_typescript_calculate.md":"XwNaAvue","src_article_imagemin.md":"B3anyYCX","cn_src_article_astparse_tokenizer.md":"BchejQ_2","cn_src_article_sort_quick_index.md":"BVLqeBLp","cn_index.md":"W0guJFQZ","cn_src_article_typescript_index.md":"4Rp9pJR0","cn_src_article_sort_radix_index.md":"BOmuPCzn","cn_src_ranui_tabs_index.md":"B7fVCz6U","src_article_javascript_domload.md":"Cfxm_7Rn","cn_src_ranui_popover_index.md":"BKOKdxfZ","cn_src_article_sort_bucket_index.md":"B2-F3jM5","src_ranui_image_index.md":"2nMskqDb","src_article_babel.md":"r59ABdaj","src_article_bundle.md":"CKZAx6pb","cn_src_article_sort_select_index.md":"ZCWAk3-H","cn_src_ranui_radar_index.md":"CbPH-Ll2","cn_src_ranui_tab_index.md":"rsyWZ2OH","cn_src_ranui_player_index.md":"DrAUxDjD","cn_src_ranui_icon_index.md":"7HxwKjnp","cn_src_ranuts_binarytree_index.md":"Ck34eB-G","src_article_designmode.md":"BpNZQVB6","cn_src_article_imagemin.md":"D-srEpzd","cn_src_ranui_skeleton_index.md":"DgTtsdks","src_article_typescript_index.md":"CfA-E8uN","cn_src_ranuts_bundler_index.md":"BDfghy_a","src_article_typescript_pattern.md":"z21_uWbS","cn_src_article_designmode.md":"B6cC8bej","cn_src_ranuts_file_appendfile.md":"KelF2awp","cn_src_ranuts_file_fileinfo.md":"CFq2jUQn","cn_src_ranuts_file_readdir.md":"BLrB46p0","cn_src_ranuts_file_readfile.md":"BLNG7IQi","cn_src_ranuts_file_watchfile.md":"BkkM-OIP","cn_src_ranuts_file_writefile.md":"CLiUndYk","cn_src_ranuts_index.md":"BfgRzSPF","cn_src_ranuts_mimetype_mimetype.md":"CE6nR7gB","cn_src_ranuts_mode_subscribe.md":"1iyG_NrT","cn_src_ranuts_utils_convertimagetobase64.md":"BWSz1fE0","cn_src_ranuts_utils_filterobj.md":"TYC5vPxZ","cn_src_ranuts_utils_formatjson.md":"Bt7mpz96","cn_src_ranuts_utils_getcookie.md":"C0ZSIXtQ","cn_src_ranuts_utils_ocr.md":"C56hL-wd","cn_src_ranuts_utils_str2xml.md":"_-Hx9tLj","cn_src_ranuts_utils_task.md":"CIEsEixO","cn_src_types_模式匹配.md":"CYaqlY6I","cn_src_types_类型运算.md":"Dpog5a1B","cn_src_types_高级类型.md":"Br8jpmEH","index.md":"CRPo-R4q","src_ranui_button_index.md":"D3RsleUR","src_ranui_checkbox_index.md":"CQiFKElf","src_article_sort_bubble_index.md":"Col1GLMV","src_ranui_message_index.md":"BtVAiAqq","src_article_sort_bucket_index.md":"CAHgx3hn","src_article_sort_count_index.md":"xmEspuny","src_article_sort_heap_index.md":"0syfn6Es","src_article_sort_index.md":"BY1uNuI9","src_article_sort_insert_index.md":"k3BrrtMz","src_article_sort_merge_index.md":"CO9oth0k","src_article_sort_quick_index.md":"ChxWvu2u","src_article_sort_radix_index.md":"DZEceG5j","cn_src_ranui_modal_index.md":"C-yweqH9","cn_src_article_functionalprogramming.md":"DGWUxfFo","cn_src_article_sort_bubble_index.md":"Bkf9kTag","cn_src_types_ts类型.md":"DXHPwTC_","cn_src_ranui_select_index.md":"BGml5oYO","cn_src_article_javascript_domload.md":"BMxMVTf2","src_ranui_loading_index.md":"ucfmJC12","cn_src_ranui_progress_index.md":"NR2Vb16q","src_ranui_icon_index.md":"DHW2RQQ9","cn_src_ranui_index.md":"Z4xw9R2O","cn_src_article_typescript_recursion.md":"BKIPR-_F","src_article_typescript_reconstruction.md":"NnML78n3","src_ranui_preview_index.md":"CCxEwrtH","src_ranui_progress_index.md":"C3cPgqUj","src_ranui_skeleton_index.md":"BF4cRoEs","src_article_sort_select_index.md":"BWzBGdQT","cn_src_ranui_preview_index.md":"BkjojaXW","cn_src_ranui_input_index.md":"B-wSLsnw","src_ranuts_binarytree_index.md":"ZO72QbNi","cn_src_article_typescript_uniontype.md":"BbHB5kPS","cn_src_ranui_loading_index.md":"BZ9JB45g","cn_src_article_sort_heap_index.md":"CBcp5l39","src_ranuts_bundler_index.md":"Bs5dChVc","src_ranui_player_index.md":"Qa6-izXs","src_ranuts_file_appendfile.md":"Cbc9IiOX","cn_src_article_sort_merge_index.md":"CC5V9E_l","src_ranui_modal_index.md":"C11OXG6Q","src_ranui_popover_index.md":"C77tXCd1","cn_src_article_sort_count_index.md":"XbDOlFNp","src_ranui_tabs_index.md":"Dkng4hGm","src_ranui_tab_index.md":"D6kmrQL4","src_ranuts_file_readfile.md":"DcYKZn9w","cn_src_article_typescript_pattern.md":"PYb4v7dD","cn_src_ranui_button_index.md":"BUvAKF5H","src_ranui_radar_index.md":"CIb6jeM8","src_ranuts_index.md":"Mkt-ZPve","src_ranui_select_index.md":"DvnlfjsK","src_ranuts_mimetype_mimetype.md":"DtTfM4JO","cn_src_ranui_message_index.md":"CaJkIwmI","src_ranuts_utils_convertimagetobase64.md":"BG_m7hJT","src_ranui_index.md":"Bee2zIH1","src_ranuts_utils_ocr.md":"CiQTOYo8","src_ranuts_utils_str2xml.md":"6dQn426O","src_article_typescript_calculate.md":"BrEQK95o","cn_src_article_bundle.md":"BYmLZV3W","src_ranuts_utils_formatjson.md":"TK4WfN4i","cn_src_ranui_image_index.md":"DRC18Kkv","src_ranuts_file_writefile.md":"CdlvVfDY","src_ranuts_file_watchfile.md":"wz67klbC","src_ranuts_utils_getcookie.md":"D73H5G3I","cn_src_article_sort_insert_index.md":"DLGoNR2E","src_ranuts_utils_task.md":"CJ2aKhmK","src_types_ts类型.md":"BF6QyHb8","src_ranuts_file_readdir.md":"W8Oz8LWA","src_ranuts_file_fileinfo.md":"BgQDUkQH","src_types_高级类型.md":"DLWejwah","cn_src_article_typescript_reconstruction.md":"Cw6neCCD","src_article_sort_shell_index.md":"dQE-fG5j","src_ranuts_mode_subscribe.md":"ChK4GBAL","src_ranuts_utils_filterobj.md":"C2Rg_UDw","src_article_astparse_tokenizer.md":"BCS9gxR1","src_ranui_input_index.md":"Dzb1htdr","src_article_typescript_recursion.md":"CliMcH-C","src_types_模式匹配.md":"BgQC7EIR","src_article_typescript_uniontype.md":"C937f1pd","cn_src_ranui_checkbox_index.md":"C0Fva9oi","src_article_functionalprogramming.md":"BynBXDCa","cn_src_article_babel.md":"D0xA2k4P","cn_src_article_sort_index.md":"B67by2HT","src_types_类型运算.md":"-22jdKRP"}
