{"index.md":"50dfb333","src_ranui_input_index.md":"56e09642","src_ranui_message_index.md":"3e8cacde","src_ranui_preview_index.md":"ead3d05d","src_ranui_skeleton_index.md":"0dbe366a","src_ranui_tab_index.md":"587ada93","src_ranui_tabs_index.md":"ceea8bec","src_ranuts_binarytree_index.md":"2902b19a","src_ranuts_bundler_index.md":"3aaba20a","src_ranuts_file_index.md":"59196ead","src_ranuts_index.md":"5ce0cb93","src_ranuts_sort_bubble_index.md":"b675d2ad","src_ranuts_sort_count_index.md":"91d5f406","src_article_astparse_tokenizer.md":"26a65990","src_article_babel.md":"e8b47eed","src_article_bundle.md":"a134889b","src_ranuts_sort_heap_index.md":"d3d6c70e","src_ranuts_sort_bucket_index.md":"42efb7a3","src_ranuts_sort_index.md":"1d48c9a6","src_article_designmode.md":"1a739a71","src_article_functionalprogramming.md":"a42d1d2c","src_article_imagemin.md":"aa22f354","src_article_javascript_domload.md":"cbe51588","src_article_typescript_calculate.md":"a9168569","src_article_typescript_index.md":"b2893431","src_article_typescript_pattern.md":"e49d95d3","src_ranui_button_index.md":"08fb0238","src_ranui_icon_index.md":"20f58daf","src_ranui_image_index.md":"a9f5fba8","src_ranui_index.md":"b1f95dcf","src_ranuts_sort_insert_index.md":"fa1639eb","src_ranuts_sort_merge_index.md":"62477f60","src_ranuts_sort_quick_index.md":"38e0334b","src_ranuts_sort_radix_index.md":"0cbd30df","src_ranuts_sort_select_index.md":"a190bc20","src_ranuts_sort_shell_index.md":"dff7d75a","src_ranuts_utils_index.md":"28841b91","src_ranuts_utils_task.md":"4fd74f50","src_article_typescript_reconstruction.md":"d0a5f75c","src_article_typescript_recursion.md":"ab5932a0","src_article_typescript_uniontype.md":"9ab9e6b6"}
