{"index.md":"c788f31a","src_article_bundle.md":"5232319a","src_article_babel.md":"79df9d07","src_article_astparse_tokenizer.md":"af293446","src_ranuts_file_index.md":"09beb2c6","src_ranuts_index.md":"b1b3fe35","src_ranuts_sort_bubble_index.md":"dc1ac161","src_ranuts_sort_bucket_index.md":"2c8ebabd","src_ranuts_sort_count_index.md":"a62b6a92","src_ranuts_sort_heap_index.md":"fef33108","src_ranuts_sort_index.md":"81c3df25","src_ranuts_sort_insert_index.md":"3132b980","src_ranuts_sort_merge_index.md":"151145a6","src_ranuts_sort_quick_index.md":"115afb65","src_ranuts_sort_radix_index.md":"d7bd87cc","src_ranuts_sort_shell_index.md":"007c7418","src_ranuts_utils_index.md":"72de0d28","src_ranuts_sort_select_index.md":"af5e11e5","src_ranuts_utils_task.md":"b590883b","src_ranui_tab_index.md":"00fe7d41","src_article_typescript_uniontype.md":"30be99d1","src_ranui_button_index.md":"51fb2f81","src_ranuts_binarytree_index.md":"9dd92191","src_ranui_icon_index.md":"9cb8bde2","src_ranui_index.md":"c19d4c63","src_ranui_message_index.md":"a5cc6aa0","src_ranui_image_index.md":"a62bd8cd","src_ranui_input_index.md":"68f0d8d5","src_ranui_modal_index.md":"0a51d1b6","src_ranui_preview_index.md":"9533363f","src_ranui_tabs_index.md":"b8811dc8","src_article_imagemin.md":"f32fec6c","src_article_typescript_recursion.md":"0f0b6ff3","src_article_javascript_domload.md":"242aa710","src_article_functionalprogramming.md":"4193afdc","src_article_typescript_index.md":"8ebaf12e","src_ranuts_bundler_index.md":"bf235e21","src_article_designmode.md":"4bb1be7c","src_article_typescript_calculate.md":"c057d53c","src_article_typescript_pattern.md":"f547efd2","src_ranui_skeleton_index.md":"8e9538ac","src_article_typescript_reconstruction.md":"c10d545b"}
