{"cn_index.md":"C92h_HpE","cn_src_article_astparse_tokenizer.md":"HdEbFody","cn_src_article_babel.md":"BvrE0wkl","cn_src_article_bundle.md":"Cd-e6H0E","cn_src_article_designmode.md":"IP5oGaPm","cn_src_article_docpreview.md":"CJqEdfmm","cn_src_article_functionalprogramming.md":"C7R-jBl3","cn_src_article_imagemin.md":"3T1VZbhU","cn_src_article_javascript_domload.md":"yHfwtyhU","cn_src_article_sort_bubble_index.md":"XSvR014d","cn_src_article_sort_bucket_index.md":"DS5GDJvM","cn_src_article_sort_count_index.md":"W1XJxAJl","cn_src_article_sort_heap_index.md":"BUzpo-6M","cn_src_article_sort_index.md":"DdVbUHTr","cn_src_article_sort_insert_index.md":"BWbyR9id","cn_src_article_sort_merge_index.md":"Cu0626Tf","cn_src_article_sort_quick_index.md":"Be2oPdVb","cn_src_article_sort_radix_index.md":"Db3lzx5R","cn_src_article_sort_select_index.md":"Cfc8xbbx","cn_src_article_sort_shell_index.md":"D8aVOzqs","cn_src_article_systemdesign.md":"C8BD9xGi","cn_src_article_typescript_calculate.md":"BqIyb8FQ","cn_src_article_typescript_index.md":"C-2_xvl5","cn_src_article_typescript_pattern.md":"BtieSfr9","cn_src_article_typescript_reconstruction.md":"BsiBbR6M","cn_src_article_typescript_recursion.md":"DuTNEp-U","cn_src_article_typescript_uniontype.md":"Cu0qI-0P","cn_src_article_video.md":"C5-wjGBT","cn_src_article_visual.md":"CP8kwO7z","cn_src_note_centos.md":"DydS8450","cn_src_note_docker.md":"C4uUHyaU","cn_src_note_libreoffice2wasm.md":"CT8sI46Q","cn_src_note_ubuntu.md":"Bi_R_D-j","cn_src_ranui_button_index.md":"kzieun6Y","cn_src_ranui_checkbox_index.md":"C543zP-b","cn_src_ranui_icon_index.md":"CEWRbUiW","cn_src_ranui_image_index.md":"BrohhRJV","cn_src_ranui_index.md":"Cl5hUmq0","cn_src_ranui_input_index.md":"B93F2Nr6","cn_src_ranui_loading_index.md":"DQcossvi","cn_src_ranui_math_index.md":"CAct-1me","cn_src_ranui_message_index.md":"2TJIpFWW","cn_src_ranui_modal_index.md":"CwvncnDr","cn_src_ranui_player_index.md":"CQ8r9S-0","cn_src_ranui_popover_index.md":"CJvQXw6Q","cn_src_ranui_preview_index.md":"BZbxYqpR","cn_src_ranui_progress_index.md":"D_Eeyyui","cn_src_ranui_radar_index.md":"D1g15qaO","cn_src_ranui_select_index.md":"DzhWqjaJ","cn_src_ranui_skeleton_index.md":"_khPN89o","cn_src_ranui_tab_index.md":"DvI2PpvP","cn_src_ranui_tabs_index.md":"C7xnKP6E","cn_src_ranuts_binarytree_index.md":"C-BuMFJv","cn_src_ranuts_bundler_index.md":"C5rEMcTS","cn_src_ranuts_file_appendfile.md":"n77iRijz","cn_src_ranuts_file_fileinfo.md":"CBzBzdCP","cn_src_ranuts_file_readdir.md":"DYokZzoM","cn_src_ranuts_file_readfile.md":"De093fJF","cn_src_ranuts_file_watchfile.md":"D0w_zZ8d","cn_src_ranuts_file_writefile.md":"Cz_vgO2r","cn_src_ranuts_index.md":"yNJY3h9C","cn_src_ranuts_mimetype_mimetype.md":"D70q9W0a","cn_src_ranuts_mode_subscribe.md":"D5FucHcy","cn_src_ranuts_utils_convertimagetobase64.md":"CfuM5gRG","cn_src_ranuts_utils_filterobj.md":"upiGSIL4","cn_src_ranuts_utils_formatjson.md":"BD7sUmLa","cn_src_ranuts_utils_getcookie.md":"DShqTbEC","cn_src_ranuts_utils_ocr.md":"ai30hY1m","cn_src_ranuts_utils_str2xml.md":"bhH-qimA","cn_src_ranuts_utils_task.md":"CbJ4VUSk","cn_src_types_ts类型.md":"DmNGAMTi","cn_src_types_模式匹配.md":"DoSLPk2M","cn_src_types_类型运算.md":"D2U-VpJq","cn_src_types_高级类型.md":"BTzLII4H","index.md":"DjmOaHqP","src_article_astparse_tokenizer.md":"DD-NBo67","src_article_babel.md":"CmMom_aI","src_article_bundle.md":"cnMWLLFn","src_article_designmode.md":"2o0Zsjyr","src_article_functionalprogramming.md":"wFqym-mi","src_article_imagemin.md":"Dg5Vrlxk","src_article_javascript_domload.md":"DWYDMTou","src_article_sort_bubble_index.md":"BC1K96e4","src_article_sort_bucket_index.md":"DS4jcBSe","src_article_sort_count_index.md":"C0pT9S4R","src_article_sort_heap_index.md":"BopLTp-L","src_article_sort_index.md":"l6Ln6ExD","src_article_sort_insert_index.md":"D0ADm98t","src_article_sort_merge_index.md":"B-Gk8eVr","src_article_sort_quick_index.md":"mNzAASsB","src_article_sort_radix_index.md":"B6DnHhNI","src_article_sort_select_index.md":"CAl3U4nN","src_article_sort_shell_index.md":"D_mAVxIv","src_article_typescript_calculate.md":"jxWCizKJ","src_article_typescript_index.md":"CEgD-M6u","src_article_typescript_pattern.md":"CskO7GQL","src_article_typescript_reconstruction.md":"BWz20VpQ","src_article_typescript_recursion.md":"-iiWs0n5","src_article_typescript_uniontype.md":"CE-PnGLx","src_ranui_button_index.md":"BkOj_PUT","src_ranui_checkbox_index.md":"Ck8fUeI2","src_ranui_icon_index.md":"CRhl6YEd","src_ranui_image_index.md":"Ovygi7JV","src_ranui_index.md":"B9KEp9dJ","src_ranui_input_index.md":"OEV749ew","src_ranui_loading_index.md":"CNcHbTbx","src_ranui_math_index.md":"DtbN8atd","src_ranui_message_index.md":"IhzcQ2d4","src_ranui_modal_index.md":"Dp6MWbuH","src_ranui_player_index.md":"Bkg_JOhB","src_ranui_popover_index.md":"Cd8-v16v","src_ranui_preview_index.md":"QFqk3N2B","src_ranui_progress_index.md":"b0PjH4ri","src_ranui_radar_index.md":"DPgCC3Cm","src_ranui_select_index.md":"BcAZ0MSC","src_ranui_skeleton_index.md":"BfsJ7VU8","src_ranui_tab_index.md":"DWzLuucI","src_ranui_tabs_index.md":"C0Ej6Yic","src_ranuts_binarytree_index.md":"CqD78GlU","src_ranuts_bundler_index.md":"BH-96oWQ","src_ranuts_file_appendfile.md":"B1BTng3I","src_ranuts_file_fileinfo.md":"CyUgGMIP","src_ranuts_file_readdir.md":"CP36Vocz","src_ranuts_file_readfile.md":"BuRW_jlx","src_ranuts_file_watchfile.md":"BrPV72kI","src_ranuts_file_writefile.md":"ZfZwwpk-","src_ranuts_index.md":"DN7MaBaC","src_ranuts_mimetype_mimetype.md":"CNpIpv6B","src_ranuts_mode_subscribe.md":"C09OPc1F","src_ranuts_utils_convertimagetobase64.md":"DfLB7bm2","src_ranuts_utils_filterobj.md":"CzapVDLc","src_ranuts_utils_formatjson.md":"D-oKxmkd","src_ranuts_utils_getcookie.md":"CUX5kHb0","src_ranuts_utils_ocr.md":"s13T5FJb","src_ranuts_utils_str2xml.md":"CeBKbUX4","src_ranuts_utils_task.md":"gNY_Efmt","src_types_ts类型.md":"dtIgLv4p","src_types_模式匹配.md":"DYv89vPw","src_types_类型运算.md":"CHZrovhs","src_types_高级类型.md":"D1GtxEO0"}
